README.md
setup.py
django_pmedien_schedule/__init__.py
django_pmedien_schedule/admin.py
django_pmedien_schedule/apps.py
django_pmedien_schedule/models.py
django_pmedien_schedule/tests.py
django_pmedien_schedule/views.py
django_pmedien_schedule.egg-info/PKG-INFO
django_pmedien_schedule.egg-info/SOURCES.txt
django_pmedien_schedule.egg-info/dependency_links.txt
django_pmedien_schedule.egg-info/requires.txt
django_pmedien_schedule.egg-info/top_level.txt
django_pmedien_schedule/addons/__init__.py
django_pmedien_schedule/addons/scheduler.py
django_pmedien_schedule/migrations/0001_initial.py
django_pmedien_schedule/migrations/__init__.py