Metadata-Version: 1.0
Name: django-pmedien-schedule
Version: 0.2
Summary: Simple schedule implementation
Home-page: http://www.pmedien.com
Author: pmedien GmbH
Author-email: nomail@pmedien.com
License: MIT
Platform: UNKNOWN
